[
  {
    "id": 1,
    "timestamp": 1664413652136,
    "products": [
      {
        "title": "microfono",
        "price": "2500",
        "timestamp": 1664397581212,
        "thumbnail": "https://es.wikipedia.org/wiki/Micr%C3%B3fono#/media/Archivo:AKG_C451B.jpg",
        "id": 3
      }
    ]
  },
  {
    "id": 2,
    "timestamp": 1664413785135,
    "products": [
      {
        "title": "microfono",
        "price": "2500",
        "timestamp": 1664397581212,
        "thumbnail": "https://es.wikipedia.org/wiki/Micr%C3%B3fono#/media/Archivo:AKG_C451B.jpg",
        "id": 3
      }
    ]
  },
  {
    "id": 3,
    "timestamp": 1664419439657,
    "products": []
  }
]